wefaas/__init__.py
wefaas/api/__init__.py
wefaas/api/fastapi_app.py
wefaas/api/fastapi_utils.py
wefaas/cli.py
wefaas/components/__init__.py
wefaas/components/outputs.py
wefaas/components/types.py
wefaas/core/__init__.py
wefaas/core/core.py
wefaas/export/__init__.py
wefaas/export/export.py
wefaas-0.0.2.dist-info/entry_points.txt
wefaas-0.0.2.dist-info/LICENSE
wefaas-0.0.2.dist-info/WHEEL
wefaas-0.0.2.dist-info/METADATA
wefaas-0.0.2.dist-info/RECORD
