Metadata-Version: 2.1
Name: wefaas
Version: 0.0.2
Summary: Turn python function into microservice.
License: Apache-2.0
Author: jiandong
Author-email: jiandong@weanalyze.co
Requires-Python: >=3.8,<4.0
Classifier: License :: OSI Approved :: Apache Software License
Classifier: Programming Language :: Python :: 3
Classifier: Programming Language :: Python :: 3.8
Classifier: Programming Language :: Python :: 3.9
Classifier: Programming Language :: Python :: 3.10
Requires-Dist: fastapi (>=0.85.1,<0.86.0)
Requires-Dist: pydantic (>=1.10.2,<2.0.0)
Requires-Dist: typer (>=0.6.1,<0.7.0)
Requires-Dist: uvicorn (>=0.18.3,<0.19.0)
